django_ai_admin_chat/__init__.py
django_ai_admin_chat/admin.py
django_ai_admin_chat/apps.py
django_ai_admin_chat/conf.py
django_ai_admin_chat/langchain_service.py
django_ai_admin_chat/models.py
django_ai_admin_chat/search.py
django_ai_admin_chat/urls.py
django_ai_admin_chat/views.py
django_ai_admin_chat/migrations/0001_embedding_cache.py
django_ai_admin_chat/migrations/0002_chathistory.py
django_ai_admin_chat/migrations/0003_chathistory_session_id_and_more.py
django_ai_admin_chat/migrations/0004_alter_chathistory_search_type.py
django_ai_admin_chat/migrations/0005_add_sql_query_to_chathistory.py
django_ai_admin_chat/migrations/0006_add_raw_sql_results_to_chathistory.py
django_ai_admin_chat/migrations/0007_remove_embedding_cache_and_search_type_embedding.py
django_ai_admin_chat/migrations/__init__.py
django_ai_admin_chat/templates/admin/base_site.html
django_ai_admin_chat-0.1.1.dist-info/licenses/LICENSE
django_ai_admin_chat-0.1.1.dist-info/METADATA
django_ai_admin_chat-0.1.1.dist-info/WHEEL
django_ai_admin_chat-0.1.1.dist-info/top_level.txt
django_ai_admin_chat-0.1.1.dist-info/RECORD
