Metadata-Version: 2.4
Name: django-ai-admin-chat
Version: 0.1.1
Summary: Django app that adds AI-powered chat to Django admin interface
Author: Patryk Maruda
License: MIT
Keywords: django,admin,ai,chat,langchain,openai
Classifier: Development Status :: 3 - Alpha
Classifier: Intended Audience :: Developers
Classifier: License :: OSI Approved :: MIT License
Classifier: Programming Language :: Python :: 3
Classifier: Programming Language :: Python :: 3.10
Classifier: Programming Language :: Python :: 3.11
Classifier: Programming Language :: Python :: 3.12
Classifier: Framework :: Django
Classifier: Framework :: Django :: 4.2
Classifier: Framework :: Django :: 5.0
Requires-Python: >=3.10
License-File: LICENSE
Requires-Dist: Django>=4.2
Requires-Dist: langchain>=0.1.0
Requires-Dist: langchain-community
Requires-Dist: langchain-experimental
Requires-Dist: langchain-openai>=0.0.5
Requires-Dist: numpy>=1.24.0
Requires-Dist: openai>=1.0.0
Requires-Dist: SQLAlchemy
Provides-Extra: dev
Requires-Dist: pytest>=7.0; extra == "dev"
Requires-Dist: pytest-django>=4.5; extra == "dev"
Dynamic: license-file
